pyowletapi/__init__.py
pyowletapi/api.py
pyowletapi/exceptions.py
pyowletapi/owlet.py
pyowletapi/sock.py
pyowletapi-2022.11.3.dist-info/METADATA
pyowletapi-2022.11.3.dist-info/WHEEL
pyowletapi-2022.11.3.dist-info/top_level.txt
pyowletapi-2022.11.3.dist-info/RECORD
